docreader/__init__.py
docreader/__main__.py
docreader/server.py
docreader/readers/__init__.py
docreader/readers/excel_reader.py
docreader/readers/pdf_reader.py
docreader/readers/word_reader.py
mcp_doc_reader-1.0.0.dist-info/METADATA
mcp_doc_reader-1.0.0.dist-info/WHEEL
mcp_doc_reader-1.0.0.dist-info/entry_points.txt
mcp_doc_reader-1.0.0.dist-info/licenses/LICENSE
mcp_doc_reader-1.0.0.dist-info/RECORD
