Metadata-Version: 2.4
Name: mcp-doc-reader
Version: 1.0.0
Summary: MCP server for reading PDF, Excel, and Word documents
Project-URL: Homepage, https://github.com/yourusername/mcp-doc-reader
Project-URL: Repository, https://github.com/yourusername/mcp-doc-reader
Project-URL: Issues, https://github.com/yourusername/mcp-doc-reader/issues
Author-email: Your Name <your.email@example.com>
License-Expression: MIT
License-File: LICENSE
Keywords: document,docx,excel,mcp,pdf,word,xlsx
Classifier: Development Status :: 4 - Beta
Classifier: Intended Audience :: Developers
Classifier: License :: OSI Approved :: MIT License
Classifier: Programming Language :: Python :: 3
Classifier: Programming Language :: Python :: 3.10
Classifier: Programming Language :: Python :: 3.11
Classifier: Programming Language :: Python :: 3.12
Requires-Python: >=3.10
Requires-Dist: mcp>=1.0.0
Requires-Dist: openpyxl>=3.1.2
Requires-Dist: pdfminer-six>=20231228
Requires-Dist: python-docx>=1.1.0
Requires-Dist: tabulate>=0.9.0
Requires-Dist: xlrd>=2.0.1
Provides-Extra: dev
Requires-Dist: pytest>=7.0.0; extra == 'dev'
Requires-Dist: ruff>=0.1.0; extra == 'dev'
